{
  "name": "dmv_healthcare",
  "title": "Dmv Healthcare",
  "licence": {
    "url": "http://opendatacommons.org/licenses/pddl",
    "name": "Open Data Commons Public Domain",
    "version": "1.0",
    "id": "odc-pddl"
  },
  "resources": [
    {
      "bytes": 2283,
      "encoding": "ISO-8859-1",
      "md5": "486c5b671667ebd50f8af601d3ae1a2b",
      "sha512": "b90a373c4c41a3acf8ff10a1276f554ee3b9c8bac9e661a389d4a437f5b70b8ae4b677f58e4c839949e68191858b802c2f403bff2d36981520d8132bb5c9b2eb",
      "format": "csv",
      "name": "counties",
      "filename": "counties.csv",
      "source": [],
      "ids": [
        {
          "variable": "GEOID"
        }
      ],
      "time": {},
      "profile": "data-resource",
      "created": "2022-01-05 21:29:16",
      "last_modified": "2022-01-03 14:43:55",
      "rowcount": 14,
      "schema": {
        "fields": [
          {
            "name": "population",
            "duplicates": 0,
            "info": {
              "long_name": "Total Population",
              "description": "Total population as estimated by the U.S. Census Bureau.",
              "statement": "There are {value} people in {features.name}.",
              "type": "count",
              "source": [
                {
                  "name": "American Community Survey",
                  "date_accessed": 2019,
                  "url": "https://www.census.gov/programs-surveys/acs.html"
                }
              ]
            },
            "type": "integer",
            "missing": 0,
            "mean": 396074.857143,
            "sd": 397196.734524,
            "min": 14128,
            "max": 1145862
          },
          {
            "name": "percent_female",
            "duplicates": 0,
            "info": {
              "long_name": "Female Percent of the Population",
              "description": "Percent of the population identified as female.",
              "statement": "{value} of the population in {features.name} identified as Female.",
              "type": "percent",
              "source": [
                {
                  "name": "American Community Survey",
                  "date_accessed": 2019,
                  "url": "https://www.census.gov/programs-surveys/acs.html"
                }
              ]
            },
            "type": "float",
            "missing": 0,
            "mean": 50.945756,
            "sd": 1.017769,
            "min": 49.347773,
            "max": 52.804224
          },
          {
            "name": "percent_white",
            "duplicates": 0,
            "type": "float",
            "missing": 0,
            "mean": 61.117939,
            "sd": 16.61527,
            "min": 17.425195,
            "max": 83.09738
          },
          {
            "name": "percent_over_49",
            "duplicates": 0,
            "info": {
              "long_name": "Older Percent of the Population",
              "description": "Percent of the population who are 50 years old or older.",
              "statement": "{value} of the population in {features.name} reported being over 49 years old.",
              "type": "percent",
              "source": [
                {
                  "name": "American Community Survey",
                  "date_accessed": 2019,
                  "url": "https://www.census.gov/programs-surveys/acs.html"
                }
              ]
            },
            "type": "float",
            "missing": 0,
            "mean": 26.196367,
            "sd": 3.348103,
            "min": 19.123398,
            "max": 31.394622
          },
          {
            "name": "access_3sfca",
            "duplicates": 0,
            "info": {
              "long_name": "Doctors (3-Step Floating Catchment Area)",
              "short_name": "Doctors (3SFCA)",
              "description": "Number of doctors available per 1,000 people, as calculated within floating catchment areas (60-minute radius) with normalized weights.",
              "statement": "There are {value} doctors available per 1,000 people in {features.name}.",
              "type": "sum",
              "citations": "wan12",
              "source": [
                {
                  "name": "American Community Survey",
                  "date_accessed": 2019,
                  "url": "https://www.census.gov/programs-surveys/acs.html"
                },
                {
                  "name": "Centers for Medicare & Medicaid Services",
                  "date_accessed": 2021,
                  "url": "https://data.cms.gov"
                }
              ]
            },
            "type": "float",
            "missing": 0,
            "mean": 2.804708,
            "sd": 1.06851,
            "min": 1.25587,
            "max": 4.376743
          },
          {
            "name": "access_2sfca",
            "duplicates": 0,
            "info": {
              "long_name": "Doctors (2-Step Floating Catchment Area)",
              "short_name": "Doctors (2SFCA)",
              "description": "Number of doctors available per 1,000 people, as calculated within floating catchment areas (60-minute radius) without normalized weights.",
              "statement": "There are {value} doctors available per 1,000 people in {features.name}.",
              "type": "sum",
              "citations": "wan12",
              "source": [
                {
                  "name": "American Community Survey",
                  "date_accessed": 2019,
                  "url": "https://www.census.gov/programs-surveys/acs.html"
                },
                {
                  "name": "Centers for Medicare & Medicaid Services",
                  "date_accessed": 2021,
                  "url": "https://data.cms.gov"
                }
              ]
            },
            "type": "float",
            "missing": 0,
            "mean": 2.855304,
            "sd": 1.255535,
            "min": 1.14906,
            "max": 4.830916
          },
          {
            "name": "access_3sfca_30",
            "duplicates": 0,
            "info": {
              "long_name": "Doctors (3-Step Floating Catchment Area Ratio, 30 minutes)",
              "short_name": "Doctors (3SFCA30)",
              "description": "Number of doctors available per 1,000 people, as calculated within smaller floating catchment areas (30-minute radius) with normalized weights.",
              "statement": "There are {value} doctors available per 1,000 people in {features.name}.",
              "type": "sum",
              "citations": "wan12",
              "source": [
                {
                  "name": "American Community Survey",
                  "date_accessed": 2019,
                  "url": "https://www.census.gov/programs-surveys/acs.html"
                },
                {
                  "name": "Centers for Medicare & Medicaid Services",
                  "date_accessed": 2021,
                  "url": "https://data.cms.gov"
                }
              ]
            },
            "type": "float",
            "missing": 0,
            "mean": 2.543267,
            "sd": 1.027274,
            "min": 1.160965,
            "max": 4.094959
          },
          {
            "name": "access_3sfca_gauss",
            "duplicates": 0,
            "info": {
              "long_name": "Doctors (3-Step Floating Catchment Area Ratio, Gaussian)",
              "short_name": "Doctors (KD3SFCA)",
              "description": "Number of doctors available per 1,000 people, as calculated within floating catchment areas (60-minute radius) with normalized, continuous weights.",
              "statement": "There are {value} doctors available per 1,000 people in {features.name}.",
              "type": "sum",
              "citations": "wan12",
              "source": [
                {
                  "name": "American Community Survey",
                  "date_accessed": 2019,
                  "url": "https://www.census.gov/programs-surveys/acs.html"
                },
                {
                  "name": "Centers for Medicare & Medicaid Services",
                  "date_accessed": 2021,
                  "url": "https://data.cms.gov"
                }
              ]
            },
            "type": "float",
            "missing": 0,
            "mean": 2.380344,
            "sd": 1.782257,
            "min": 0.038719,
            "max": 6.823407
          },
          {
            "name": "access_3sfca_commute",
            "duplicates": 0,
            "info": {
              "long_name": "Doctors (3-Step Floating Catchment Area Ratio, commuter-based)",
              "short_name": "Doctors (CB3SFCA)",
              "description": "Number of doctors available per 1,000 people, as calculated within floating catchment areas (60-minute radius) with normalized weights adjusted for multiple origins (home and work).",
              "statement": "There are {value} doctors available per 1,000 people in {features.name}.",
              "type": "sum",
              "citations": "wan12",
              "source": [
                {
                  "name": "American Community Survey",
                  "date_accessed": 2019,
                  "url": "https://www.census.gov/programs-surveys/acs.html"
                },
                {
                  "name": "Centers for Medicare & Medicaid Services",
                  "date_accessed": 2021,
                  "url": "https://data.cms.gov"
                },
                {
                  "name": "Longitudinal Employer-Household Dynamics",
                  "date_accessed": 2019,
                  "url": "https://lehd.ces.census.gov"
                }
              ]
            },
            "type": "float",
            "missing": 0,
            "mean": 2.87101,
            "sd": 1.086688,
            "min": 1.301819,
            "max": 4.450477
          }
        ]
      },
      "_references": {
        "lou09": {
          "author": [
            {
              "given": "Wei",
              "family": "Lou"
            },
            {
              "given": "Yi",
              "family": "Qi"
            }
          ],
          "year": 2009,
          "title": "An enhanced two-step floating catchment area (e2sfca) method for measuring spatial accessibility to primary care physicians",
          "journal": "Health & Place",
          "volume": 15,
          "page": "1100-1107",
          "doi": "10.1016/j.healthplace.2009.06.002"
        },
        "wan12": {
          "author": [
            {
              "given": "Neng",
              "family": "Wan"
            },
            {
              "given": "Bin",
              "family": "Zou"
            },
            {
              "given": "Troy",
              "family": "Sternberg"
            }
          ],
          "year": 2012,
          "title": "A three-step floating catchment area method for analyzing spatial access to health services",
          "journal": "International Journal of Geographical Information Science",
          "volume": 26,
          "page": "1073-1089",
          "doi": "10.1080/13658816.2011.624987"
        }
      }
    },
    {
      "bytes": 190158,
      "encoding": "ISO-8859-1",
      "md5": "7921466ec0f1b5b944e79525d5a00b9f",
      "sha512": "4420b46a10c5552d79f389b16dcb6bea520cf56f20b657fe3d132555b7b54018150076dbdbf5a80eed7253772a4612fa996a3d055980688a7010930ffbc7fea7",
      "format": "csv",
      "name": "tracts",
      "filename": "tracts.csv",
      "source": [],
      "ids": [
        {
          "variable": "GEOID"
        }
      ],
      "time": {},
      "profile": "data-resource",
      "created": "2022-01-05 21:29:14",
      "last_modified": "2022-01-03 14:35:22",
      "rowcount": 1218,
      "schema": {
        "fields": [
          {
            "name": "population",
            "duplicates": 122,
            "info": {
              "long_name": "Total Population",
              "description": "Total population as estimated by the U.S. Census Bureau.",
              "statement": "There are {value} people in {features.name}.",
              "type": "count",
              "source": [
                {
                  "name": "American Community Survey",
                  "date_accessed": 2019,
                  "url": "https://www.census.gov/programs-surveys/acs.html"
                }
              ]
            },
            "type": "integer",
            "missing": 0,
            "mean": 4552.584565,
            "sd": 1879.751689,
            "min": 4,
            "max": 19438
          },
          {
            "name": "percent_female",
            "duplicates": 0,
            "info": {
              "long_name": "Female Percent of the Population",
              "description": "Percent of the population identified as female.",
              "statement": "{value} of the population in {features.name} identified as Female.",
              "type": "percent",
              "source": [
                {
                  "name": "American Community Survey",
                  "date_accessed": 2019,
                  "url": "https://www.census.gov/programs-surveys/acs.html"
                }
              ]
            },
            "type": "float",
            "missing": 0,
            "mean": 51.254191,
            "sd": 4.717738,
            "min": 0,
            "max": 100
          },
          {
            "name": "percent_white",
            "duplicates": 4,
            "type": "float",
            "missing": 0,
            "mean": 51.568119,
            "sd": 27.11683,
            "min": 0,
            "max": 100
          },
          {
            "name": "percent_over_49",
            "duplicates": 1,
            "info": {
              "long_name": "Older Percent of the Population",
              "description": "Percent of the population who are 50 years old or older.",
              "statement": "{value} of the population in {features.name} reported being over 49 years old.",
              "type": "percent",
              "source": [
                {
                  "name": "American Community Survey",
                  "date_accessed": 2019,
                  "url": "https://www.census.gov/programs-surveys/acs.html"
                }
              ]
            },
            "type": "float",
            "missing": 0,
            "mean": 27.043573,
            "sd": 9.089308,
            "min": 0,
            "max": 100
          },
          {
            "name": "access_3sfca",
            "duplicates": 378,
            "info": {
              "long_name": "Doctors (3-Step Floating Catchment Area)",
              "short_name": "Doctors (3SFCA)",
              "description": "Number of doctors available per 1,000 people, as calculated within floating catchment areas (60-minute radius) with normalized weights.",
              "statement": "There are {value} doctors available per 1,000 people in {features.name}.",
              "type": "sum",
              "citations": "wan12",
              "source": [
                {
                  "name": "American Community Survey",
                  "date_accessed": 2019,
                  "url": "https://www.census.gov/programs-surveys/acs.html"
                },
                {
                  "name": "Centers for Medicare & Medicaid Services",
                  "date_accessed": 2021,
                  "url": "https://data.cms.gov"
                }
              ]
            },
            "type": "float",
            "missing": 0,
            "mean": 3.048006,
            "sd": 1.969652,
            "min": 0.562315,
            "max": 51.072153
          },
          {
            "name": "access_2sfca",
            "duplicates": 377,
            "info": {
              "long_name": "Doctors (2-Step Floating Catchment Area)",
              "short_name": "Doctors (2SFCA)",
              "description": "Number of doctors available per 1,000 people, as calculated within floating catchment areas (60-minute radius) without normalized weights.",
              "statement": "There are {value} doctors available per 1,000 people in {features.name}.",
              "type": "sum",
              "citations": "wan12",
              "source": [
                {
                  "name": "American Community Survey",
                  "date_accessed": 2019,
                  "url": "https://www.census.gov/programs-surveys/acs.html"
                },
                {
                  "name": "Centers for Medicare & Medicaid Services",
                  "date_accessed": 2021,
                  "url": "https://data.cms.gov"
                }
              ]
            },
            "type": "float",
            "missing": 0,
            "mean": 3.074172,
            "sd": 1.863807,
            "min": 0.520646,
            "max": 46.941058
          },
          {
            "name": "access_3sfca_30",
            "duplicates": 383,
            "info": {
              "long_name": "Doctors (3-Step Floating Catchment Area Ratio, 30 minutes)",
              "short_name": "Doctors (3SFCA30)",
              "description": "Number of doctors available per 1,000 people, as calculated within smaller floating catchment areas (30-minute radius) with normalized weights.",
              "statement": "There are {value} doctors available per 1,000 people in {features.name}.",
              "type": "sum",
              "citations": "wan12",
              "source": [
                {
                  "name": "American Community Survey",
                  "date_accessed": 2019,
                  "url": "https://www.census.gov/programs-surveys/acs.html"
                },
                {
                  "name": "Centers for Medicare & Medicaid Services",
                  "date_accessed": 2021,
                  "url": "https://data.cms.gov"
                }
              ]
            },
            "type": "float",
            "missing": 0,
            "mean": 2.92842,
            "sd": 1.625337,
            "min": 0.44456,
            "max": 39.302476
          },
          {
            "name": "access_3sfca_gauss",
            "duplicates": 369,
            "info": {
              "long_name": "Doctors (3-Step Floating Catchment Area Ratio, Gaussian)",
              "short_name": "Doctors (KD3SFCA)",
              "description": "Number of doctors available per 1,000 people, as calculated within floating catchment areas (60-minute radius) with normalized, continuous weights.",
              "statement": "There are {value} doctors available per 1,000 people in {features.name}.",
              "type": "sum",
              "citations": "wan12",
              "source": [
                {
                  "name": "American Community Survey",
                  "date_accessed": 2019,
                  "url": "https://www.census.gov/programs-surveys/acs.html"
                },
                {
                  "name": "Centers for Medicare & Medicaid Services",
                  "date_accessed": 2021,
                  "url": "https://data.cms.gov"
                }
              ]
            },
            "type": "float",
            "missing": 0,
            "mean": 2.93988,
            "sd": 5.668513,
            "min": 0,
            "max": 66.163731
          },
          {
            "name": "access_3sfca_commute",
            "duplicates": 0,
            "info": {
              "long_name": "Doctors (3-Step Floating Catchment Area Ratio, commuter-based)",
              "short_name": "Doctors (CB3SFCA)",
              "description": "Number of doctors available per 1,000 people, as calculated within floating catchment areas (60-minute radius) with normalized weights adjusted for multiple origins (home and work).",
              "statement": "There are {value} doctors available per 1,000 people in {features.name}.",
              "type": "sum",
              "citations": "wan12",
              "source": [
                {
                  "name": "American Community Survey",
                  "date_accessed": 2019,
                  "url": "https://www.census.gov/programs-surveys/acs.html"
                },
                {
                  "name": "Centers for Medicare & Medicaid Services",
                  "date_accessed": 2021,
                  "url": "https://data.cms.gov"
                },
                {
                  "name": "Longitudinal Employer-Household Dynamics",
                  "date_accessed": 2019,
                  "url": "https://lehd.ces.census.gov"
                }
              ]
            },
            "type": "float",
            "missing": 0,
            "mean": 3.068047,
            "sd": 1.890591,
            "min": 0.681982,
            "max": 47.423702
          }
        ]
      },
      "_references": {
        "lou09": {
          "author": [
            {
              "given": "Wei",
              "family": "Lou"
            },
            {
              "given": "Yi",
              "family": "Qi"
            }
          ],
          "year": 2009,
          "title": "An enhanced two-step floating catchment area (e2sfca) method for measuring spatial accessibility to primary care physicians",
          "journal": "Health & Place",
          "volume": 15,
          "page": "1100-1107",
          "doi": "10.1016/j.healthplace.2009.06.002"
        },
        "wan12": {
          "author": [
            {
              "given": "Neng",
              "family": "Wan"
            },
            {
              "given": "Bin",
              "family": "Zou"
            },
            {
              "given": "Troy",
              "family": "Sternberg"
            }
          ],
          "year": 2012,
          "title": "A three-step floating catchment area method for analyzing spatial access to health services",
          "journal": "International Journal of Geographical Information Science",
          "volume": 26,
          "page": "1073-1089",
          "doi": "10.1080/13658816.2011.624987"
        }
      }
    },
    {
      "bytes": 499385,
      "encoding": "ISO-8859-1",
      "md5": "4105c53f8565a1b5ce72b40366ad9a10",
      "sha512": "73f02bd59e5641b40c53d84c43f66cf430db7ca8f3e8fca84dd04614a9e7219218aa2afa460be18d548b2f5e27ef768504774d6cdf71d2615860829111532c8b",
      "format": "csv",
      "name": "blockgroups",
      "filename": "blockgroups.csv",
      "source": [],
      "ids": [
        {
          "variable": "GEOID"
        }
      ],
      "time": {},
      "profile": "data-resource",
      "created": "2022-01-05 21:27:22",
      "last_modified": "2022-01-03 14:39:35",
      "rowcount": 3235,
      "schema": {
        "fields": [
          {
            "name": "population",
            "duplicates": 1357,
            "info": {
              "long_name": "Total Population",
              "description": "Total population as estimated by the U.S. Census Bureau.",
              "statement": "There are {value} people in {features.name}.",
              "type": "count",
              "source": [
                {
                  "name": "American Community Survey",
                  "date_accessed": 2019,
                  "url": "https://www.census.gov/programs-surveys/acs.html"
                }
              ]
            },
            "type": "integer",
            "missing": 0,
            "mean": 1714.079753,
            "sd": 877.078436,
            "min": 4,
            "max": 8987
          },
          {
            "name": "percent_female",
            "duplicates": 44,
            "info": {
              "long_name": "Female Percent of the Population",
              "description": "Percent of the population identified as female.",
              "statement": "{value} of the population in {features.name} identified as Female.",
              "type": "percent",
              "source": [
                {
                  "name": "American Community Survey",
                  "date_accessed": 2019,
                  "url": "https://www.census.gov/programs-surveys/acs.html"
                }
              ]
            },
            "type": "float",
            "missing": 0,
            "mean": 51.29108,
            "sd": 6.111047,
            "min": 0,
            "max": 100
          },
          {
            "name": "percent_white",
            "duplicates": 71,
            "type": "float",
            "missing": 0,
            "mean": 53.10363,
            "sd": 28.332358,
            "min": 0,
            "max": 100
          },
          {
            "name": "percent_over_49",
            "duplicates": 45,
            "info": {
              "long_name": "Older Percent of the Population",
              "description": "Percent of the population who are 50 years old or older.",
              "statement": "{value} of the population in {features.name} reported being over 49 years old.",
              "type": "percent",
              "source": [
                {
                  "name": "American Community Survey",
                  "date_accessed": 2019,
                  "url": "https://www.census.gov/programs-surveys/acs.html"
                }
              ]
            },
            "type": "float",
            "missing": 0,
            "mean": 27.1344,
            "sd": 11.236291,
            "min": 0,
            "max": 100
          },
          {
            "name": "access_3sfca",
            "duplicates": 1713,
            "info": {
              "long_name": "Doctors (3-Step Floating Catchment Area)",
              "short_name": "Doctors (3SFCA)",
              "description": "Number of doctors available per 1,000 people, as calculated within floating catchment areas (60-minute radius) with normalized weights.",
              "statement": "There are {value} doctors available per 1,000 people in {features.name}.",
              "type": "sum",
              "citations": "wan12",
              "source": [
                {
                  "name": "American Community Survey",
                  "date_accessed": 2019,
                  "url": "https://www.census.gov/programs-surveys/acs.html"
                },
                {
                  "name": "Centers for Medicare & Medicaid Services",
                  "date_accessed": 2021,
                  "url": "https://data.cms.gov"
                }
              ]
            },
            "type": "float",
            "missing": 0,
            "mean": 3.105912,
            "sd": 6.06875,
            "min": 0.307735,
            "max": 337.120041
          },
          {
            "name": "access_2sfca",
            "duplicates": 1713,
            "info": {
              "long_name": "Doctors (2-Step Floating Catchment Area)",
              "short_name": "Doctors (2SFCA)",
              "description": "Number of doctors available per 1,000 people, as calculated within floating catchment areas (60-minute radius) without normalized weights.",
              "statement": "There are {value} doctors available per 1,000 people in {features.name}.",
              "type": "sum",
              "citations": "wan12",
              "source": [
                {
                  "name": "American Community Survey",
                  "date_accessed": 2019,
                  "url": "https://www.census.gov/programs-surveys/acs.html"
                },
                {
                  "name": "Centers for Medicare & Medicaid Services",
                  "date_accessed": 2021,
                  "url": "https://data.cms.gov"
                }
              ]
            },
            "type": "float",
            "missing": 0,
            "mean": 3.13428,
            "sd": 6.00948,
            "min": 0.295432,
            "max": 335.215138
          },
          {
            "name": "access_3sfca_30",
            "duplicates": 1719,
            "info": {
              "long_name": "Doctors (3-Step Floating Catchment Area Ratio, 30 minutes)",
              "short_name": "Doctors (3SFCA30)",
              "description": "Number of doctors available per 1,000 people, as calculated within smaller floating catchment areas (30-minute radius) with normalized weights.",
              "statement": "There are {value} doctors available per 1,000 people in {features.name}.",
              "type": "sum",
              "citations": "wan12",
              "source": [
                {
                  "name": "American Community Survey",
                  "date_accessed": 2019,
                  "url": "https://www.census.gov/programs-surveys/acs.html"
                },
                {
                  "name": "Centers for Medicare & Medicaid Services",
                  "date_accessed": 2021,
                  "url": "https://data.cms.gov"
                }
              ]
            },
            "type": "float",
            "missing": 0,
            "mean": 2.91367,
            "sd": 2.053077,
            "min": 0.186466,
            "max": 91.806355
          },
          {
            "name": "access_3sfca_gauss",
            "duplicates": 1699,
            "info": {
              "long_name": "Doctors (3-Step Floating Catchment Area Ratio, Gaussian)",
              "short_name": "Doctors (KD3SFCA)",
              "description": "Number of doctors available per 1,000 people, as calculated within floating catchment areas (60-minute radius) with normalized, continuous weights.",
              "statement": "There are {value} doctors available per 1,000 people in {features.name}.",
              "type": "sum",
              "citations": "wan12",
              "source": [
                {
                  "name": "American Community Survey",
                  "date_accessed": 2019,
                  "url": "https://www.census.gov/programs-surveys/acs.html"
                },
                {
                  "name": "Centers for Medicare & Medicaid Services",
                  "date_accessed": 2021,
                  "url": "https://data.cms.gov"
                }
              ]
            },
            "type": "float",
            "missing": 0,
            "mean": 3.001084,
            "sd": 7.736583,
            "min": 0,
            "max": 214.460201
          },
          {
            "name": "access_3sfca_commute",
            "duplicates": 0,
            "info": {
              "long_name": "Doctors (3-Step Floating Catchment Area Ratio, commuter-based)",
              "short_name": "Doctors (CB3SFCA)",
              "description": "Number of doctors available per 1,000 people, as calculated within floating catchment areas (60-minute radius) with normalized weights adjusted for multiple origins (home and work).",
              "statement": "There are {value} doctors available per 1,000 people in {features.name}.",
              "type": "sum",
              "citations": "wan12",
              "source": [
                {
                  "name": "American Community Survey",
                  "date_accessed": 2019,
                  "url": "https://www.census.gov/programs-surveys/acs.html"
                },
                {
                  "name": "Centers for Medicare & Medicaid Services",
                  "date_accessed": 2021,
                  "url": "https://data.cms.gov"
                },
                {
                  "name": "Longitudinal Employer-Household Dynamics",
                  "date_accessed": 2019,
                  "url": "https://lehd.ces.census.gov"
                }
              ]
            },
            "type": "float",
            "missing": 0,
            "mean": 3.126752,
            "sd": 5.847289,
            "min": 0.438188,
            "max": 324.977993
          }
        ]
      },
      "_references": {
        "lou09": {
          "author": [
            {
              "given": "Wei",
              "family": "Lou"
            },
            {
              "given": "Yi",
              "family": "Qi"
            }
          ],
          "year": 2009,
          "title": "An enhanced two-step floating catchment area (e2sfca) method for measuring spatial accessibility to primary care physicians",
          "journal": "Health & Place",
          "volume": 15,
          "page": "1100-1107",
          "doi": "10.1016/j.healthplace.2009.06.002"
        },
        "wan12": {
          "author": [
            {
              "given": "Neng",
              "family": "Wan"
            },
            {
              "given": "Bin",
              "family": "Zou"
            },
            {
              "given": "Troy",
              "family": "Sternberg"
            }
          ],
          "year": 2012,
          "title": "A three-step floating catchment area method for analyzing spatial access to health services",
          "journal": "International Journal of Geographical Information Science",
          "volume": 26,
          "page": "1073-1089",
          "doi": "10.1080/13658816.2011.624987"
        }
      }
    }
  ]
}
